Metadata-Version: 1.1
Name: bluerobotics-tsys01
Version: 0.0.1
Summary: A python module for the TSYS01 digital temperature sensor
Home-page: https://www.bluerobotics.com
Author: Blue Robotics
Author-email: support@bluerobotics.com
License: UNKNOWN
Platform: UNKNOWN
Classifier: Programming Language :: Python
Classifier: License :: OSI Approved :: MIT License
Classifier: Operating System :: OS Independent
